complex_valued_transformer/__init__.py
complex_valued_transformer/attend.py
complex_valued_transformer/autoregressive_wrapper.py
complex_valued_transformer/complex_valued_transformer.py
complex_valued_transformer-0.0.14.dist-info/LICENSE
complex_valued_transformer-0.0.14.dist-info/METADATA
complex_valued_transformer-0.0.14.dist-info/WHEEL
complex_valued_transformer-0.0.14.dist-info/top_level.txt
complex_valued_transformer-0.0.14.dist-info/RECORD
