Metadata-Version: 2.1
Name: complex-valued-transformer
Version: 0.0.14
Summary: Complex Valued Transformer / Attention
Home-page: https://github.com/lucidrains/complex-valued-transformer
Author: Phil Wang
Author-email: lucidrains@gmail.com
License: MIT
Keywords: artificial intelligence,deep learning,attention mechanisms,transformers,complex domain
Classifier: Development Status :: 4 - Beta
Classifier: Intended Audience :: Developers
Classifier: Topic :: Scientific/Engineering :: Artificial Intelligence
Classifier: License :: OSI Approved :: MIT License
Classifier: Programming Language :: Python :: 3.6
License-File: LICENSE
Requires-Dist: einops >=0.7.0
Requires-Dist: torch >=1.12
